stringint.py
stringint-0.1.0.dist-info/DESCRIPTION.rst
stringint-0.1.0.dist-info/METADATA
stringint-0.1.0.dist-info/RECORD
stringint-0.1.0.dist-info/WHEEL
stringint-0.1.0.dist-info/metadata.json
stringint-0.1.0.dist-info/top_level.txt
