Metadata-Version: 2.0
Name: stringint
Version: 0.1.0
Summary: represent strings as ints and vice versa
Home-page: https://github.com/DasIch/stringint/
Author: Daniel Neuhäuser
Author-email: ich@danielneuhaeuser.de
License: UNKNOWN
Platform: UNKNOWN
Classifier: License :: OSI Approved :: BSD License
Classifier: Programming Language :: Python :: 3.5
Classifier: Programming Language :: Python :: Implementation :: CPython
